pymensor/__init__.py
pymensor/gpib.py
pymensor-0.0.2.dist-info/LICENSE
pymensor-0.0.2.dist-info/METADATA
pymensor-0.0.2.dist-info/WHEEL
pymensor-0.0.2.dist-info/top_level.txt
pymensor-0.0.2.dist-info/RECORD
