Metadata-Version: 2.1
Name: pymensor
Version: 0.0.2
Summary: Python driver for Mensor Modular Pressure Controllers.
Home-page: https://github.com/stevenlowery011/pymensor.git
Author: Steven Lowery
Author-email: steven.lowery011@gmail.com
License: GPLv3
Platform: UNKNOWN
Classifier: License :: OSI Approved :: GNU General Public License v3 (GPLv3)
Classifier: Development Status :: 3 - Alpha
Classifier: Natural Language :: English
Classifier: Programming Language :: Python :: 3
Classifier: Topic :: Scientific/Engineering :: Human Machine Interfaces
Classifier: Topic :: Scientific/Engineering :: Electronic Design Automation (EDA)
Requires-Dist: pyvisa
